{
    "created_time": "2024-03-25T08:11:24Z",
    "files": [
        {
            "attachment_folder": "",
            "created_time": "2024-03-25T08:11:51Z",
            "id": "63",
            "modified_time": "2024-03-25T08:17:32Z",
            "name": "FPGA边缘检测（上升沿、下降沿、双边沿）的三种实现方案.md",
            "signature": "784285915001467335",
            "tags": [
            ]
        }
    ],
    "folders": [
    ],
    "id": "62",
    "modified_time": "2024-03-25T08:11:24Z",
    "signature": "207324077699500",
    "version": 3
}
